data_agent/__init__.py
data_agent/abstract_connector.py
data_agent/api.py
data_agent/config_manager.py
data_agent/connection_manager.py
data_agent/daq_scheduler.py
data_agent/exceptions.py
data_agent/exchanger.py
data_agent/groups_aware_connector.py
data_agent/history_harvester.py
data_agent/local_agent.py
data_agent/local_cli.py
data_agent/msg_packer.py
data_agent/safe_manipulator.py
data_agent/broker/__init__.py
data_agent/broker/agent.py
data_agent/broker/agent_main.py
data_agent/broker/cli.py
data_agent/broker/instr_exec.py
data_agent/broker/instr_list_services.py
data_agent/connectors/fake_connector.py
data_agent/linux/__init__.py
data_agent/linux/config_default.yaml
data_agent/win32/__init__.py
data_agent/win32/config_default.yaml
data_agent/win32/service.py
data_agent/win32/win_logger.py
data_agent/win32/win_service.py
data_agent/win32/hooks/__init__.py
data_agent/win32/hooks/hook-data_agent.py
data_agent-0.4.0.dist-info/licenses/LICENSE.txt
data_agent-0.4.0.dist-info/METADATA
data_agent-0.4.0.dist-info/WHEEL
data_agent-0.4.0.dist-info/entry_points.txt
data_agent-0.4.0.dist-info/top_level.txt
data_agent-0.4.0.dist-info/RECORD
