Metadata-Version: 2.4
Name: data-agent
Version: 0.4.0
Summary: Data Agent is a python library for pipelining real-time and historical data to and from industrial historians and control systems
Home-page: https://github.com/imubit/data-agent/
Author: Meir Tseitlin
License: LGPLv3
Project-URL: Documentation, https://github.com/imubit/data-agent/
Platform: any
Classifier: Development Status :: 4 - Beta
Classifier: Programming Language :: Python
License-File: LICENSE.txt
Requires-Dist: dynaconf
Requires-Dist: pandas
Requires-Dist: msgpack
Requires-Dist: zstandard
Requires-Dist: aiomisc
Requires-Dist: aiodebug
Requires-Dist: apscheduler
Requires-Dist: cachetools
Requires-Dist: amqp-fabric
Requires-Dist: pywin32>=1.0; platform_system == "Windows"
Provides-Extra: testing
Requires-Dist: setuptools; extra == "testing"
Requires-Dist: pytest; extra == "testing"
Requires-Dist: pytest-cov; extra == "testing"
Requires-Dist: pytest-asyncio==0.26.0; extra == "testing"
Requires-Dist: aiomisc-pytest; extra == "testing"
Dynamic: license-file
